scaevola/__init__.py
scaevola/core/__init__.py
scaevola/core/cfg.toml
scaevola/tests/__init__.py
scaevola/tests/test_doc.py
scaevola/tests/test_op.py
scaevola/tests/test_slots_Scaevola.py
scaevola/tests/test_slots_auto.py
scaevola-1.1.2.dist-info/licenses/LICENSE.txt
scaevola-1.1.2.dist-info/METADATA
scaevola-1.1.2.dist-info/WHEEL
scaevola-1.1.2.dist-info/top_level.txt
scaevola-1.1.2.dist-info/RECORD
